eventsourcing_helpers/__init__.py
eventsourcing_helpers/command_handler.py
eventsourcing_helpers/compat.py
eventsourcing_helpers/consumer.py
eventsourcing_helpers/event_handler.py
eventsourcing_helpers/handler.py
eventsourcing_helpers/metrics.py
eventsourcing_helpers/models.py
eventsourcing_helpers/serializers.py
eventsourcing_helpers/utils.py
eventsourcing_helpers/message/__init__.py
eventsourcing_helpers/message/message.py
eventsourcing_helpers/message/pydantic.py
eventsourcing_helpers/messagebus/__init__.py
eventsourcing_helpers/messagebus/backends/__init__.py
eventsourcing_helpers/messagebus/backends/kafka/__init__.py
eventsourcing_helpers/messagebus/backends/kafka/config.py
eventsourcing_helpers/messagebus/backends/kafka/offset_watchdog/__init__.py
eventsourcing_helpers/messagebus/backends/kafka/offset_watchdog/backends/__init__.py
eventsourcing_helpers/messagebus/backends/kafka/offset_watchdog/backends/memory/__init__.py
eventsourcing_helpers/messagebus/backends/kafka/offset_watchdog/backends/null/__init__.py
eventsourcing_helpers/messagebus/backends/kafka/offset_watchdog/backends/redis/__init__.py
eventsourcing_helpers/messagebus/backends/mock/__init__.py
eventsourcing_helpers/messagebus/backends/mock/backend.py
eventsourcing_helpers/messagebus/backends/mock/backend_compat.py
eventsourcing_helpers/messagebus/backends/mock/test.py
eventsourcing_helpers/messagebus/backends/mock/utils.py
eventsourcing_helpers/repository/__init__.py
eventsourcing_helpers/repository/builder.py
eventsourcing_helpers/repository/backends/__init__.py
eventsourcing_helpers/repository/backends/kafka/__init__.py
eventsourcing_helpers/repository/backends/kafka/config.py
eventsourcing_helpers/repository/snapshot/__init__.py
eventsourcing_helpers/repository/snapshot/config.py
eventsourcing_helpers/repository/snapshot/serializers.py
eventsourcing_helpers/repository/snapshot/backends/__init__.py
eventsourcing_helpers/repository/snapshot/backends/mongo/__init__.py
eventsourcing_helpers-2.3.0.dist-info/METADATA
eventsourcing_helpers-2.3.0.dist-info/WHEEL
eventsourcing_helpers-2.3.0.dist-info/entry_points.txt
eventsourcing_helpers-2.3.0.dist-info/top_level.txt
eventsourcing_helpers-2.3.0.dist-info/RECORD
