Metadata-Version: 2.4
Name: eventsourcing-helpers
Version: 2.3.0
Summary: Helpers for practicing the Event sourcing pattern
Home-page: https://github.com/fyndiq/eventsourcing_helpers
Author: Fyndiq AB
Author-email: support@fyndiq.com
License: MIT
Requires-Dist: structlog>=17.2.0
Requires-Dist: jsonpickle>=0.9.6
Requires-Dist: confluent-kafka-helpers>=1.0.0
Provides-Extra: mongo
Requires-Dist: pymongo>=3.6.1; extra == "mongo"
Provides-Extra: redis
Requires-Dist: redis>=2.10.6; extra == "redis"
Requires-Dist: hiredis>=0.2.0; extra == "redis"
Provides-Extra: cnamedtuple
Requires-Dist: cnamedtuple>=0.1.6; extra == "cnamedtuple"
Provides-Extra: pydantic
Requires-Dist: pydantic>=2; extra == "pydantic"
Dynamic: author
Dynamic: author-email
Dynamic: home-page
Dynamic: license
Dynamic: provides-extra
Dynamic: requires-dist
Dynamic: summary
